dance_video_toolkit/__init__.py
dance_video_toolkit/dance_toolkit.py
dance_video_toolkit/log.py
dance_video_toolkit/model_manager.py
dance_video_toolkit/optimized_pos.py
dance_video_toolkit/optimized_video_processor.py
dance_video_toolkit-1.0.0.dist-info/licenses/LICENSE
dance_video_toolkit-1.0.0.dist-info/METADATA
dance_video_toolkit-1.0.0.dist-info/WHEEL
dance_video_toolkit-1.0.0.dist-info/entry_points.txt
dance_video_toolkit-1.0.0.dist-info/top_level.txt
dance_video_toolkit-1.0.0.dist-info/RECORD
