Metadata-Version: 2.4
Name: dance-video-toolkit
Version: 1.0.0
Summary: AI-powered dance video processing toolkit for filtering multi-person videos and splitting dance clips
Author-email: Dance Toolkit Team <dance@example.com>
License: MIT License
Project-URL: Homepage, https://github.com/yourusername/dance-video-toolkit
Project-URL: Documentation, https://github.com/yourusername/dance-video-toolkit/blob/main/README.md
Project-URL: Repository, https://github.com/yourusername/dance-video-toolkit.git
Project-URL: Issues, https://github.com/yourusername/dance-video-toolkit/issues
Keywords: dance,video,ai,pose-detection,video-processing,yolo,ultralytics
Classifier: Development Status :: 5 - Production/Stable
Classifier: Intended Audience :: Developers
Classifier: Intended Audience :: End Users/Desktop
Classifier: License :: OSI Approved :: MIT License
Classifier: Operating System :: OS Independent
Classifier: Programming Language :: Python :: 3
Classifier: Programming Language :: Python :: 3.8
Classifier: Programming Language :: Python :: 3.9
Classifier: Programming Language :: Python :: 3.10
Classifier: Programming Language :: Python :: 3.11
Classifier: Programming Language :: Python :: 3.12
Classifier: Topic :: Multimedia :: Video
Classifier: Topic :: Scientific/Engineering :: Artificial Intelligence
Requires-Python: >=3.8
License-File: LICENSE
Requires-Dist: opencv-python>=4.8.0
Requires-Dist: ultralytics>=8.0.0
Requires-Dist: torch>=1.13.0
Requires-Dist: torchvision>=0.14.0
Requires-Dist: numpy==1.26.2
Requires-Dist: requests>=2.25.0
Requires-Dist: tqdm>=4.60.0
Provides-Extra: dev
Requires-Dist: pytest>=7.0.0; extra == "dev"
Requires-Dist: pytest-cov>=4.0.0; extra == "dev"
Requires-Dist: black>=22.0.0; extra == "dev"
Requires-Dist: isort>=5.10.0; extra == "dev"
Requires-Dist: flake8>=5.0.0; extra == "dev"
Requires-Dist: mypy>=1.0.0; extra == "dev"
Dynamic: license-file
